simulated_bifurcation/__init__.py
simulated_bifurcation/simulated_bifurcation.py
simulated_bifurcation/core/__init__.py
simulated_bifurcation/core/ising.py
simulated_bifurcation/core/optimization_domain.py
simulated_bifurcation/core/quadratic_polynomial.py
simulated_bifurcation/core/utils.py
simulated_bifurcation/core/variable.py
simulated_bifurcation/models/__init__.py
simulated_bifurcation/models/abc_model.py
simulated_bifurcation/models/ising.py
simulated_bifurcation/models/markowitz.py
simulated_bifurcation/models/number_partitioning.py
simulated_bifurcation/models/qubo.py
simulated_bifurcation/optimizer/__init__.py
simulated_bifurcation/optimizer/environment.py
simulated_bifurcation/optimizer/simulated_bifurcation_engine.py
simulated_bifurcation/optimizer/simulated_bifurcation_optimizer.py
simulated_bifurcation/optimizer/stop_window.py
simulated_bifurcation/optimizer/symplectic_integrator.py
simulated_bifurcation-2.0.0.dist-info/licenses/LICENSE
simulated_bifurcation-2.0.0.dist-info/METADATA
simulated_bifurcation-2.0.0.dist-info/WHEEL
simulated_bifurcation-2.0.0.dist-info/top_level.txt
simulated_bifurcation-2.0.0.dist-info/RECORD
