Metadata-Version: 2.4
Name: simulated-bifurcation
Version: 2.0.0
Summary: Efficient implementation of the quantum-inspired Simulated Bifurcation (SB) algorithm to solve Ising-like problems.
Home-page: https://github.com/bqth29/simulated-bifurcation-algorithm
Classifier: Programming Language :: Python :: 3
Classifier: License :: OSI Approved :: MIT License
Classifier: Operating System :: Microsoft :: Windows
Classifier: Operating System :: Unix
Classifier: Operating System :: MacOS
Classifier: Topic :: Scientific/Engineering
Classifier: Intended Audience :: Science/Research
Requires-Python: >=3.8
License-File: LICENSE
Requires-Dist: numpy>=2.0.0
Requires-Dist: sympy
Requires-Dist: torch>=2.2.0
Requires-Dist: tqdm
Provides-Extra: lint
Requires-Dist: black; extra == "lint"
Requires-Dist: flake8; extra == "lint"
Requires-Dist: isort; extra == "lint"
Provides-Extra: test
Requires-Dist: coverage; extra == "test"
Requires-Dist: pytest; extra == "test"
Provides-Extra: dev
Requires-Dist: sphinx; extra == "dev"
Requires-Dist: numpydoc; extra == "dev"
Requires-Dist: furo; extra == "dev"
Requires-Dist: myst-parser; extra == "dev"
Requires-Dist: black; extra == "dev"
Requires-Dist: flake8; extra == "dev"
Requires-Dist: isort; extra == "dev"
Requires-Dist: coverage; extra == "dev"
Requires-Dist: pytest; extra == "dev"
Provides-Extra: all
Requires-Dist: sphinx; extra == "all"
Requires-Dist: numpydoc; extra == "all"
Requires-Dist: furo; extra == "all"
Requires-Dist: myst-parser; extra == "all"
Requires-Dist: black; extra == "all"
Requires-Dist: flake8; extra == "all"
Requires-Dist: isort; extra == "all"
Requires-Dist: coverage; extra == "all"
Requires-Dist: pytest; extra == "all"
Provides-Extra: docs
Requires-Dist: sphinx; extra == "docs"
Requires-Dist: numpydoc; extra == "docs"
Requires-Dist: furo; extra == "docs"
Requires-Dist: myst-parser; extra == "docs"
Dynamic: classifier
Dynamic: description
Dynamic: description-content-type
Dynamic: home-page
Dynamic: license-file
Dynamic: provides-extra
Dynamic: requires-dist
Dynamic: requires-python
Dynamic: summary
